turbofm/__init__.py
turbofm/__main__.py
turbofm/filter/__init__.py
turbofm/filter/__main__.py
turbofm/lastid/__init__.py
turbofm/lastid/__main__.py
turbofm/mailbox/__init__.py
turbofm/mailbox/export/__init__.py
turbofm/mailbox/export/__main__.py
turbofm/scan/__init__.py
turbofm/scan/__main__.py
turbofm/send/__init__.py
turbofm/send/minimal/__init__.py
turbofm/send/minimal/__main__.py
turbofm/send/plain/__init__.py
turbofm/send/plain/__main__.py
turbofm/trigger/__init__.py
turbofm/trigger/thunderbird.py
turbofm-0.31.1.dist-info/licenses/LICENSE
turbofm-0.31.1.dist-info/METADATA
turbofm-0.31.1.dist-info/WHEEL
turbofm-0.31.1.dist-info/top_level.txt
turbofm-0.31.1.dist-info/RECORD
