Metadata-Version: 2.4
Name: turbofm
Version: 0.31.1
Summary: A small example package
Author-email: Robert Degen <turbodev@mailbox.org>
Project-URL: Homepage, https://github.com/turbo-bert
Project-URL: Issues, https://github.com/turbo-bert
Classifier: Programming Language :: Python :: 3
Classifier: License :: OSI Approved :: MIT License
Classifier: Operating System :: OS Independent
Requires-Python: >=3.8
License-File: LICENSE
Requires-Dist: rich
Requires-Dist: xler8
Requires-Dist: requests
Requires-Dist: html2text
Dynamic: license-file
